fpbot/__init__.py
fpbot/api.py
fpbot/baseline.py
fpbot/check_files.py
fpbot/clean_lc.py
fpbot/connectors.py
fpbot/credentials.py
fpbot/data/blacklist_ZTF_g.dat
fpbot/data/blacklist_ZTF_i.dat
fpbot/data/blacklist_ZTF_r.dat
fpbot/data/gBandRefImages.txt
fpbot/data/logo.png
fpbot/data/marshal_dummyfile.csv
fpbot/data/reference.csv
fpbot/data/slackbot_icon.jpg
fpbot/data/zp_thresholds_quadID.txt
fpbot/data/ztf_host_w_redshift_20190510.csv
fpbot/data/ztfg_eff.dat
fpbot/data/ztfi_eff.dat
fpbot/data/ztfr_eff.dat
fpbot/database.py
fpbot/example_download.dat
fpbot/pipeline.py
fpbot/plot.py
fpbot/thumbnails.py
fpbot/utils.py
fpbot-1.1.3.dist-info/LICENSE
fpbot-1.1.3.dist-info/METADATA
fpbot-1.1.3.dist-info/WHEEL
fpbot-1.1.3.dist-info/entry_points.txt
fpbot-1.1.3.dist-info/RECORD
