Metadata-Version: 2.1
Name: fpbot
Version: 1.1.3
Summary: Forced photometry pipeline for the Zwicky Transient Facility
Home-page: https://github.com/simeonreusch/fpbot
License: BSD-3-Clause
Author: simeonreusch
Author-email: simeon.reusch@desy.de
Maintainer: Simeon Reusch
Maintainer-email: simeon.reusch@desy.de
Requires-Python: >=3.10,<4
Classifier: License :: OSI Approved :: BSD License
Classifier: Operating System :: OS Independent
Classifier: Programming Language :: Python :: 3
Classifier: Programming Language :: Python :: 3.10
Classifier: Programming Language :: Python :: 3.11
Provides-Extra: slack
Requires-Dist: SQLAlchemy (>=1.4.39,<3.0.0)
Requires-Dist: astropy (>=5.1,<6.0)
Requires-Dist: backoff (>=2.1.2,<3.0.0)
Requires-Dist: fastapi (>=0.79,<0.102)
Requires-Dist: keyring (>=23.7,<25.0)
Requires-Dist: matplotlib (>=3.5.2,<4.0.0)
Requires-Dist: mypy (>=0.991,<1.6)
Requires-Dist: numpy (>=1.23.1,<2.0.0)
Requires-Dist: pandas (>=1.4.3,<2.0.0)
Requires-Dist: pymongo (>=4.2.0,<5.0.0)
Requires-Dist: requests (>=2.28.1,<3.0.0)
Requires-Dist: scipy (>=1.8.1,<2.0.0)
Requires-Dist: sfdmap (>=0.1.1,<0.2.0)
Requires-Dist: slackclient (>=2.9.4,<3.0.0) ; extra == "slack"
Requires-Dist: tdqm (>=0.0.1,<0.0.2)
Requires-Dist: ztflc (>=0.3.1,<0.4.0)
Requires-Dist: ztfquery (>=1.18.4,<2.0.0)
Project-URL: Repository, https://github.com/simeonreusch/fpbot
